tmath1/__init__.py
tmath1-0.0.1.dist-info/METADATA
tmath1-0.0.1.dist-info/WHEEL
tmath1-0.0.1.dist-info/top_level.txt
tmath1-0.0.1.dist-info/RECORD
