Metadata-Version: 2.1
Name: tmath1
Version: 0.0.1
Summary: The math module includes a wide range of functions that cover various mathematical operations.
Author: Taus Hasan (Taus Hasan)
Author-email: <taushasan704@gmail.com>
Keywords: python,mathematics,calculate,math
Classifier: Development Status :: 1 - Planning
Classifier: Intended Audience :: Developers
Classifier: Programming Language :: Python :: 3
Classifier: Operating System :: Unix
Classifier: Operating System :: MacOS :: MacOS X
Classifier: Operating System :: Microsoft :: Windows
